quick_slack/__init__.py
quick_slack/cli.py
quick_slack/config.json
quick_slack/low_api.py
quick_slack/utils.py
quick_slack-1.0.1.dist-info/METADATA
quick_slack-1.0.1.dist-info/WHEEL
quick_slack-1.0.1.dist-info/entry_points.txt
quick_slack-1.0.1.dist-info/top_level.txt
quick_slack-1.0.1.dist-info/RECORD
